hbp_knowledge/__init__.py
hbp_knowledge/__main__.py
hbp_knowledge/_cache.bel.json
hbp_knowledge/albuquerque2009.bel
hbp_knowledge/albuquerque2009.bel.json
hbp_knowledge/alderman2018.bel
hbp_knowledge/baumann1993.bel
hbp_knowledge/baumann1993.bel.json
hbp_knowledge/bengoa2017.bel
hbp_knowledge/bengoa2017.bel.json
hbp_knowledge/biswas2016.bel
hbp_knowledge/biswas2016.bel.json
hbp_knowledge/boland2018.bel
hbp_knowledge/boland2018.bel.json
hbp_knowledge/brehme2014.bel
hbp_knowledge/brehme2014.bel.json
hbp_knowledge/buckingham2009.bel
hbp_knowledge/buckingham2009.bel.json
hbp_knowledge/bulic2012.bel
hbp_knowledge/bulic2012.bel.json
hbp_knowledge/caballero2018.bel
hbp_knowledge/caballero2018.bel.json
hbp_knowledge/cabrales2017.bel
hbp_knowledge/cabrales2017.bel.json
hbp_knowledge/changeux2012.bel
hbp_knowledge/changeux2012.bel.json
hbp_knowledge/chesser2013.bel
hbp_knowledge/chesser2013.bel.json
hbp_knowledge/choi2014.bel
hbp_knowledge/choi2014.bel.json
hbp_knowledge/ciechanover2013.bel
hbp_knowledge/ciechanover2013.bel.json
hbp_knowledge/cox2016.bel
hbp_knowledge/cox2016.bel.json
hbp_knowledge/damesquita2018.bel
hbp_knowledge/damesquita2018.bel.json
hbp_knowledge/dani2007.bel
hbp_knowledge/dani2007.bel.json
hbp_knowledge/dani2015.bel
hbp_knowledge/dani2015.bel.json
hbp_knowledge/defelice2008.bel
hbp_knowledge/defelice2008.bel.json
hbp_knowledge/dennissen2016.bel
hbp_knowledge/dennissen2016.bel.json
hbp_knowledge/despres2017.bel
hbp_knowledge/despres2017.bel.json
hbp_knowledge/dinopoulou2013.bel
hbp_knowledge/dinopoulou2013.bel.json
hbp_knowledge/elliott2018.bel
hbp_knowledge/elliott2018.bel.json
hbp_knowledge/evans2018.bel
hbp_knowledge/evans2018.bel.json
hbp_knowledge/ferreira-vieira2016.bel
hbp_knowledge/ferreira-vieira2016.bel.json
hbp_knowledge/francis2016.bel
hbp_knowledge/francis2016.bel.json
hbp_knowledge/frandemiche2014.bel
hbp_knowledge/frandemiche2014.bel.json
hbp_knowledge/gant2018.bel
hbp_knowledge/gant2018.bel.json
hbp_knowledge/heneka2017.bel
hbp_knowledge-0.0.7.dist-info/LICENSE
hbp_knowledge-0.0.7.dist-info/METADATA
hbp_knowledge-0.0.7.dist-info/WHEEL
hbp_knowledge-0.0.7.dist-info/entry_points.txt
hbp_knowledge-0.0.7.dist-info/top_level.txt
hbp_knowledge-0.0.7.dist-info/RECORD
