Metadata-Version: 2.1
Name: hbp-knowledge
Version: 0.0.7
Summary: Knowledge curated in BEL from full text during the Human Brain Pharmacome project
Home-page: https://github.com/pharmacome/knowledge
Author: Charles Tapley Hoyt
Author-email: charles.hoyt@scai.fraunhofer.de
Maintainer: Charles Tapley Hoyt
Maintainer-email: charles.hoyt@scai.fraunhofer.de
License: MIT License
Download-URL: https://github.com/pharmacome/knowledge/releases
Project-URL: Bug Tracker, https://github.com/pharmacome/knowledge/issues
Project-URL: Source Code, https://github.com/pharmacome/knowledge
Keywords: Biological Expression Language,BEL,Domain Specific Language,DSL,Systems biology,Networks biology,Drug repositioning
Platform: UNKNOWN
Classifier: Development Status :: 4 - Beta
Classifier: Environment :: Console
Classifier: Intended Audience :: Developers
Classifier: Intended Audience :: Science/Research
Classifier: Operating System :: OS Independent
Classifier: License :: OSI Approved :: MIT License
Classifier: Programming Language :: Python
Classifier: Programming Language :: Python :: 3.7
Classifier: Programming Language :: Python :: 3.6
Classifier: Programming Language :: Python :: 3 :: Only
Classifier: Topic :: Scientific/Engineering :: Bio-Informatics
Classifier: Topic :: Scientific/Engineering :: Chemistry
Requires-Python: >=3.6
Requires-Dist: bel-repository (>=0.0.7)
